README.md
setup.py
cesarmodulo/__init__.py
cesarmodulo/definiciones.py
cesarmodulo/funciones.py
cesarmodulo.egg-info/PKG-INFO
cesarmodulo.egg-info/SOURCES.txt
cesarmodulo.egg-info/dependency_links.txt
cesarmodulo.egg-info/top_level.txt