Metadata-Version: 2.1
Name: cesarmodulo
Version: 0.1
Summary: Esta es la descripcion de mi paquete
Home-page: https://github.com/Cesar-Crespo/cesarmodulo.git
Author: Cesar Crespo
Author-email: cesar2crespo@gmail.com
License: MIT
Keywords: testing,logging,example
